{
  "project_info": {
    "project_number": "344309233140",
    "firebase_url": "https://soccer-legends-db.firebaseio.com",
    "project_id": "soccer-legends-db",
    "storage_bucket": "soccer-legends-db.appspot.com"
  },
  "client": [
    {
      "client_info": {
        "mobilesdk_app_id": "1:344309233140:android:6b7776ad7a45f28e5e75a1",
        "android_client_info": {
          "package_name": "com.Company.SoccerLegends"
        }
      },
      "oauth_client": [
        {
          "client_id": "344309233140-97q01ale47qs5g5qbuo9vq66icea09sg.apps.googleusercontent.com",
          "client_type": 1,
          "android_info": {
            "package_name": "com.Company.SoccerLegends",
            "certificate_hash": "d670a0d736c244e94b4a5976bc0f3f161f8bc459"
          }
        },
        {
          "client_id": "344309233140-jmgom7qvdqdvo292jqltr5ok64mh9t8b.apps.googleusercontent.com",
          "client_type": 3
        }
      ],
      "api_key": [
        {
          "current_key": "AIzaSyDIcOlSeH8p9HayUtPy_HIcfFH_IyCIE48"
        }
      ],
      "services": {
        "appinvite_service": {
          "other_platform_oauth_client": [
            {
              "client_id": "344309233140-jmgom7qvdqdvo292jqltr5ok64mh9t8b.apps.googleusercontent.com",
              "client_type": 3
            }
          ]
        }
      }
    }
  ],
  "configuration_version": "1"
}